{
  "tgt_word2id": {
    "": 11,
    "you": 15,
    "And": 25,
    "<pad>": 0,
    "--": 8,
    "what": 26,
    "say": 17,
    "this": 16,
    "for": 12,
    "on": 18,
    "and": 14,
    "<s>": 1,
    "all": 22,
    "a": 6,
    "have": 10,
    "the": 7,
    "we": 27,
    "of": 9,
    "little": 29,
    "in": 13,
    "to": 5,
    "been": 24,
    "like": 21,
    "my": 20,
    "sob)": 30,
    "I": 4,
    "</s>": 2,
    "(Mock": 28,
    "<unk>": 3,
    "me.": 31,
    "story": 23,
    "it": 19
  },
  "src_word2id": {
    "": 10,
    "es": 20,
    "parte": 18,
    "una": 13,
    "<pad>": 0,
    "--": 4,
    "la": 11,
    "Y": 19,
    "<s>": 1,
    "de": 5,
    "a": 8,
    "para": 9,
    "que": 6,
    "(Sollozos": 24,
    "y": 14,
    "fingidos)": 23,
    "este": 16,
    "</s>": 2,
    "por": 12,
    "lo": 15,
    "Nashville": 25,
    "en": 7,
    "<unk>": 3,
    "el": 22,
    "un": 17,
    "historia": 21
  }
}